pyvisacharts/__init__.py
pyvisacharts/_version.py
pyvisacharts/charts.py
pyvisacharts/labextension/package.json
pyvisacharts/labextension/static/488.dafa3b4d2d79578c06ef.js
pyvisacharts/labextension/static/488.dafa3b4d2d79578c06ef.js.LICENSE.txt
pyvisacharts/labextension/static/764.c55cabc6ead9889a039d.js
pyvisacharts/labextension/static/872.7226ef16ed0ec2fb8e43.js
pyvisacharts/labextension/static/remoteEntry.042d71cf9e3a9b43641b.js
pyvisacharts/labextension/static/style.js
pyvisacharts/labextension/static/third-party-licenses.json
pyvisacharts/nbextension/extension.js
pyvisacharts/nbextension/index.js
pyvisacharts/nbextension/index.js.LICENSE.txt
pyvisacharts-3.0.1.data/data/etc/jupyter/nbconfig/notebook.d/charts-python.json
pyvisacharts-3.0.1.data/data/share/jupyter/labextensions/@visa/charts-python/install.json
pyvisacharts-3.0.1.data/data/share/jupyter/labextensions/@visa/charts-python/package.json
pyvisacharts-3.0.1.data/data/share/jupyter/labextensions/@visa/charts-python/static/488.dafa3b4d2d79578c06ef.js
pyvisacharts-3.0.1.data/data/share/jupyter/labextensions/@visa/charts-python/static/488.dafa3b4d2d79578c06ef.js.LICENSE.txt
pyvisacharts-3.0.1.data/data/share/jupyter/labextensions/@visa/charts-python/static/764.c55cabc6ead9889a039d.js
pyvisacharts-3.0.1.data/data/share/jupyter/labextensions/@visa/charts-python/static/872.7226ef16ed0ec2fb8e43.js
pyvisacharts-3.0.1.data/data/share/jupyter/labextensions/@visa/charts-python/static/remoteEntry.042d71cf9e3a9b43641b.js
pyvisacharts-3.0.1.data/data/share/jupyter/labextensions/@visa/charts-python/static/style.js
pyvisacharts-3.0.1.data/data/share/jupyter/labextensions/@visa/charts-python/static/third-party-licenses.json
pyvisacharts-3.0.1.data/data/share/jupyter/nbextensions/@visa/charts-python/extension.js
pyvisacharts-3.0.1.data/data/share/jupyter/nbextensions/@visa/charts-python/index.js
pyvisacharts-3.0.1.data/data/share/jupyter/nbextensions/@visa/charts-python/index.js.LICENSE.txt
pyvisacharts-3.0.1.dist-info/LICENSE
pyvisacharts-3.0.1.dist-info/METADATA
pyvisacharts-3.0.1.dist-info/WHEEL
pyvisacharts-3.0.1.dist-info/top_level.txt
pyvisacharts-3.0.1.dist-info/RECORD
