Metadata-Version: 2.1
Name: pyvisacharts
Version: 3.0.1
Summary: A Jupyter Widget for Visa Chart Components
Home-page: https://github.com/visa/visa-chart-components/tree/main/packages/charts-python
Author: Visa Data Experience Team
License: SEE LICENSE IN LICENSE
Project-URL: Bug Reports, https://github.com/visa/visa-chart-components/issues
Project-URL: Source, https://github.com/visa/visa-chart-components/tree/main/packages/charts-python
Project-URL: Storybook Demo, https://visa.github.io/visa-chart-components/
Project-URL: Visa Chart Components, https://github.com/visa/visa-chart-components
Keywords: ipython,jupyter,widgets,visa,charts,visualization,viz,accessibility,a11y,d3
Classifier: Development Status :: 4 - Beta
Classifier: Framework :: IPython
Classifier: Intended Audience :: Developers
Classifier: Intended Audience :: Science/Research
Classifier: Topic :: Multimedia :: Graphics
Classifier: License :: OSI Approved :: MIT License
Classifier: Programming Language :: Python :: 3.6
Classifier: Programming Language :: Python :: 3.7
Classifier: Programming Language :: Python :: 3.8
Classifier: Programming Language :: Python :: 3.9
License-File: LICENSE
Requires-Dist: ipywidgets>=7.6.0
